{
  "generator-jhipster": {
    "applicationType": "monolith",
    "gitHubOrganization": "emmanuelnkosi",
    "baseName": "jhipsterSampleApplication",
    "packageName": "io.github.jhipster.application",
    "serverPort": 8085,
    "serviceDiscoveryType": false,
    "authenticationType": "jwt",
    "uaaBaseName": "../uaa",
    "hibernateCache": "ehcache",
    "clusteredHttpSession": false,
    "websocket": false,
    "databaseType": "sql",
    "devDatabaseType": "h2Disk",
    "prodDatabaseType": "mysql",
    "searchEngine": false,
    "enableSwaggerCodegen": "true",
    "messageBroker": "kafka",
    "buildTool": "maven",
    "enableSocialSignIn": true,
    "useSass": false,
    "clientPackageManager": "yarn",
    "testFrameworks": [],
    "enableTranslation": false,
    "nativeLanguage": "en",
    "languages": [
      "en"
    ],
    "clientFramework": "angular1",
    "jhipsterVersion": "4.10.2",
    "packageFolder": "io/github/jhipster/application",
    "jwtSecretKey": "2fc63cafaaf961f8f287aab726a66f31d7184cbb",
    "jhiPrefix": "jhi"
  }
}